[{
    "ID": 0,
    "Countries": "AD - Andorra"
}, {
    "ID": 1,
    "Countries": "AE - United Arab Emirates"
}, {
    "ID": 2,
    "Countries": "AF - Afghanistan"
}, {
    "ID": 3,
    "Countries": "AG - Antigua and Barbuda"
}, {
    "ID": 4,
    "Countries": "AI - Anguilla"
}, {
    "ID": 5,
    "Countries": "AL - Albania"
}, {
    "ID": 6,
    "Countries": "AM - Armenia"
}, {
    "ID": 7,
    "Countries": "AO - Angola"
}, {
    "ID": 8,
    "Countries": "AQ - Antarctica"
}, {
    "ID": 9,
    "Countries": "AR - Argentina"
}, {
    "ID": 10,
    "Countries": "AS - American Samoa"
}, {
    "ID": 11,
    "Countries": "AT - Austria"
}, {
    "ID": 12,
    "Countries": "AU - Australia"
}, {
    "ID": 13,
    "Countries": "AW - Aruba"
}, {
    "ID": 14,
    "Countries": "AZ - Azerbaijan"
}, {
    "ID": 15,
    "Countries": "BA - Bosnia and Herzegovina"
}, {
    "ID": 16,
    "Countries": "BB - Barbados"
}, {
    "ID": 17,
    "Countries": "BD - Bangladesh"
}, {
    "ID": 18,
    "Countries": "BE - Belgium"
}, {
    "ID": 19,
    "Countries": "BF - Burkina Faso"
}, {
    "ID": 20,
    "Countries": "BG - Bulgaria"
}, {
    "ID": 21,
    "Countries": "BH - Bahrain"
}, {
    "ID": 22,
    "Countries": "BI - Burundi"
}, {
    "ID": 23,
    "Countries": "BJ - Benin"
}, {
    "ID": 24,
    "Countries": "BL - Saint Barthélemy"
}, {
    "ID": 25,
    "Countries": "BM - Bermuda"
}, {
    "ID": 26,
    "Countries": "BN - Brunei"
}, {
    "ID": 27,
    "Countries": "BO - Bolivia"
}, {
    "ID": 28,
    "Countries": "BQ - Caribbean Netherlands"
}, {
    "ID": 29,
    "Countries": "BR - Brazil"
}, {
    "ID": 30,
    "Countries": "BS - Bahamas"
}, {
    "ID": 31,
    "Countries": "BT - Bhutan"
}, {
    "ID": 32,
    "Countries": "BW - Botswana"
}, {
    "ID": 33,
    "Countries": "BY - Belarus"
}, {
    "ID": 34,
    "Countries": "BZ - Belize"
}, {
    "ID": 35,
    "Countries": "CA - Canada"
}, {
    "ID": 36,
    "Countries": "CC - Cocos (Keeling) Islands"
}, {
    "ID": 37,
    "Countries": "CD - Congo (Kinshasa)"
}, {
    "ID": 38,
    "Countries": "CF - Central African Republic"
}, {
    "ID": 39,
    "Countries": "CG - Congo (Brazzaville)"
}, {
    "ID": 40,
    "Countries": "CH - Switzerland"
}, {
    "ID": 41,
    "Countries": "CI - Côte d'Ivoire"
}, {
    "ID": 42,
    "Countries": "CK - Cook Islands"
}, {
    "ID": 43,
    "Countries": "CL - Chile"
}, {
    "ID": 44,
    "Countries": "CM - Cameroon"
}, {
    "ID": 45,
    "Countries": "CN - China"
}, {
    "ID": 46,
    "Countries": "CO - Colombia"
}, {
    "ID": 47,
    "Countries": "CR - Costa Rica"
}, {
    "ID": 48,
    "Countries": "CU - Cuba"
}, {
    "ID": 49,
    "Countries": "CV - Cape Verde"
}, {
    "ID": 50,
    "Countries": "CW - Curaçao"
}, {
    "ID": 51,
    "Countries": "CX - Christmas Island"
}, {
    "ID": 52,
    "Countries": "CY - Cyprus"
}, {
    "ID": 53,
    "Countries": "CZ - Czech Republic"
}, {
    "ID": 54,
    "Countries": "DE - Germany"
}, {
    "ID": 55,
    "Countries": "DJ - Djibouti"
}, {
    "ID": 56,
    "Countries": "DK - Denmark"
}, {
    "ID": 57,
    "Countries": "DM - Dominica"
}, {
    "ID": 58,
    "Countries": "DO - Dominican Republic"
}, {
    "ID": 59,
    "Countries": "DZ - Algeria"
}, {
    "ID": 60,
    "Countries": "EC - Ecuador"
}, {
    "ID": 61,
    "Countries": "EE - Estonia"
}, {
    "ID": 62,
    "Countries": "EG - Egypt"
}, {
    "ID": 63,
    "Countries": "EH - Western Sahara"
}, {
    "ID": 64,
    "Countries": "ER - Eritrea"
}, {
    "ID": 65,
    "Countries": "ES - Spain"
}, {
    "ID": 66,
    "Countries": "ET - Ethiopia"
}, {
    "ID": 67,
    "Countries": "FI - Finland"
}, {
    "ID": 68,
    "Countries": "FJ - Fiji"
}, {
    "ID": 69,
    "Countries": "FK - Falkland Islands"
}, {
    "ID": 70,
    "Countries": "FM - Micronesia"
}, {
    "ID": 71,
    "Countries": "FO - Faroe Islands"
}, {
    "ID": 72,
    "Countries": "FR - France"
}, {
    "ID": 73,
    "Countries": "GA - Gabon"
}, {
    "ID": 74,
    "Countries": "GB - United Kingdom"
}, {
    "ID": 75,
    "Countries": "GD - Grenada"
}, {
    "ID": 76,
    "Countries": "GE - Georgia"
}, {
    "ID": 77,
    "Countries": "GF - French Guiana"
}, {
    "ID": 78,
    "Countries": "GG - Guernsey"
}, {
    "ID": 79,
    "Countries": "GH - Ghana"
}, {
    "ID": 80,
    "Countries": "GI - Gibraltar"
}, {
    "ID": 81,
    "Countries": "GL - Greenland"
}, {
    "ID": 82,
    "Countries": "GM - Gambia"
}, {
    "ID": 83,
    "Countries": "GN - Guinea"
}, {
    "ID": 84,
    "Countries": "GP - Guadeloupe"
}, {
    "ID": 85,
    "Countries": "GQ - Equatorial Guinea"
}, {
    "ID": 86,
    "Countries": "GR - Greece"
}, {
    "ID": 87,
    "Countries": "GS - South Georgia and the South Sandwich Islands"
}, {
    "ID": 88,
    "Countries": "GT - Guatemala"
}, {
    "ID": 89,
    "Countries": "GU - Guam"
}, {
    "ID": 90,
    "Countries": "GW - Guinea-Bissau"
}, {
    "ID": 91,
    "Countries": "GY - Guyana"
}, {
    "ID": 92,
    "Countries": "HK - Hong Kong"
}, {
    "ID": 93,
    "Countries": "HN - Honduras"
}, {
    "ID": 94,
    "Countries": "HR - Croatia"
}, {
    "ID": 95,
    "Countries": "HT - Haiti"
}, {
    "ID": 96,
    "Countries": "HU - Hungary"
}, {
    "ID": 97,
    "Countries": "ID - Indonesia"
}, {
    "ID": 98,
    "Countries": "IE - Ireland"
}, {
    "ID": 99,
    "Countries": "IL - Israel"
}, {
    "ID": 100,
    "Countries": "IM - Isle of Man"
}, {
    "ID": 101,
    "Countries": "IN - India"
}, {
    "ID": 102,
    "Countries": "IO - British Indian Ocean Territory"
}, {
    "ID": 103,
    "Countries": "IQ - Iraq"
}, {
    "ID": 104,
    "Countries": "IR - Iran"
}, {
    "ID": 105,
    "Countries": "IS - Iceland"
}, {
    "ID": 106,
    "Countries": "IT - Italy"
}, {
    "ID": 107,
    "Countries": "JE - Jersey"
}, {
    "ID": 108,
    "Countries": "JM - Jamaica"
}, {
    "ID": 109,
    "Countries": "JO - Jordan"
}, {
    "ID": 110,
    "Countries": "JP - Japan"
}, {
    "ID": 111,
    "Countries": "KE - Kenya"
}, {
    "ID": 112,
    "Countries": "KG - Kyrgyzstan"
}, {
    "ID": 113,
    "Countries": "KH - Cambodia"
}, {
    "ID": 114,
    "Countries": "KI - Kiribati"
}, {
    "ID": 115,
    "Countries": "KM - Comoros"
}, {
    "ID": 116,
    "Countries": "KN - Saint Kitts and Nevis"
}, {
    "ID": 117,
    "Countries": "KP - North Korea"
}, {
    "ID": 118,
    "Countries": "KR - South Korea"
}, {
    "ID": 119,
    "Countries": "KW - Kuwait"
}, {
    "ID": 120,
    "Countries": "KY - Cayman Islands"
}, {
    "ID": 121,
    "Countries": "KZ - Kazakhstan"
}, {
    "ID": 122,
    "Countries": "LA - Laos"
}, {
    "ID": 123,
    "Countries": "LB - Lebanon"
}, {
    "ID": 124,
    "Countries": "LC - Saint Lucia"
}, {
    "ID": 125,
    "Countries": "LI - Liechtenstein"
}, {
    "ID": 126,
    "Countries": "LK - Sri Lanka"
}, {
    "ID": 127,
    "Countries": "LR - Liberia"
}, {
    "ID": 128,
    "Countries": "LS - Lesotho"
}, {
    "ID": 129,
    "Countries": "LT - Lithuania"
}, {
    "ID": 130,
    "Countries": "LU - Luxembourg"
}, {
    "ID": 131,
    "Countries": "LV - Latvia"
}, {
    "ID": 132,
    "Countries": "LY - Libya"
}, {
    "ID": 133,
    "Countries": "MA - Morocco"
}, {
    "ID": 134,
    "Countries": "MC - Monaco"
}, {
    "ID": 135,
    "Countries": "MD - Moldova"
}, {
    "ID": 136,
    "Countries": "ME - Montenegro"
}, {
    "ID": 137,
    "Countries": "MF - Saint Martin"
}, {
    "ID": 138,
    "Countries": "MG - Madagascar"
}, {
    "ID": 139,
    "Countries": "MH - Marshall Islands"
}, {
    "ID": 140,
    "Countries": "MK - North Macedonia"
}, {
    "ID": 141,
    "Countries": "ML - Mali"
}, {
    "ID": 142,
    "Countries": "MM - Burma"
}, {
    "ID": 143,
    "Countries": "MN - Mongolia"
}, {
    "ID": 144,
    "Countries": "MO - Macau"
}, {
    "ID": 145,
    "Countries": "MP - Northern Mariana Islands"
}, {
    "ID": 146,
    "Countries": "MQ - Martinique"
}, {
    "ID": 147,
    "Countries": "MR - Mauritania"
}, {
    "ID": 148,
    "Countries": "MS - Montserrat"
}, {
    "ID": 149,
    "Countries": "MT - Malta"
}, {
    "ID": 150,
    "Countries": "MU - Mauritius"
}, {
    "ID": 151,
    "Countries": "MV - Maldives"
}, {
    "ID": 152,
    "Countries": "MW - Malawi"
}, {
    "ID": 153,
    "Countries": "MX - Mexico"
}, {
    "ID": 154,
    "Countries": "MY - Malaysia"
}, {
    "ID": 155,
    "Countries": "MZ - Mozambique"
}, {
    "ID": 156,
    "Countries": NaN
}, {
    "ID": 157,
    "Countries": "NC - New Caledonia"
}, {
    "ID": 158,
    "Countries": "NE - Niger"
}, {
    "ID": 159,
    "Countries": "NF - Norfolk Island"
}, {
    "ID": 160,
    "Countries": "NG - Nigeria"
}, {
    "ID": 161,
    "Countries": "NI - Nicaragua"
}, {
    "ID": 162,
    "Countries": "NL - Netherlands"
}, {
    "ID": 163,
    "Countries": "NO - Norway"
}, {
    "ID": 164,
    "Countries": "NP - Nepal"
}, {
    "ID": 165,
    "Countries": "NR - Nauru"
}, {
    "ID": 166,
    "Countries": "NU - Niue"
}, {
    "ID": 167,
    "Countries": "NZ - New Zealand"
}, {
    "ID": 168,
    "Countries": "OM - Oman"
}, {
    "ID": 169,
    "Countries": "PA - Panama"
}, {
    "ID": 170,
    "Countries": "PE - Perú"
}, {
    "ID": 171,
    "Countries": "PF - French Polynesia"
}, {
    "ID": 172,
    "Countries": "PG - Papua New Guinea"
}, {
    "ID": 173,
    "Countries": "PH - Philippines"
}, {
    "ID": 174,
    "Countries": "PK - Pakistan"
}, {
    "ID": 175,
    "Countries": "PL - Poland"
}, {
    "ID": 176,
    "Countries": "PM - Saint Pierre and Miquelon"
}, {
    "ID": 177,
    "Countries": "PN - Pitcairn"
}, {
    "ID": 178,
    "Countries": "PR - Puerto Rico"
}, {
    "ID": 179,
    "Countries": "PS - Palestinian Territory"
}, {
    "ID": 180,
    "Countries": "PT - Portugal"
}, {
    "ID": 181,
    "Countries": "PW - Palau"
}, {
    "ID": 182,
    "Countries": "PY - Paraguay"
}, {
    "ID": 183,
    "Countries": "QA - Qatar"
}, {
    "ID": 184,
    "Countries": "RE - Réunion"
}, {
    "ID": 185,
    "Countries": "RO - Romania"
}, {
    "ID": 186,
    "Countries": "RS - Serbia"
}, {
    "ID": 187,
    "Countries": "RU - Russia"
}, {
    "ID": 188,
    "Countries": "RW - Rwanda"
}, {
    "ID": 189,
    "Countries": "SA - Saudi Arabia"
}, {
    "ID": 190,
    "Countries": "SB - Solomon Islands"
}, {
    "ID": 191,
    "Countries": "SC - Seychelles"
}, {
    "ID": 192,
    "Countries": "SD - Sudan"
}, {
    "ID": 193,
    "Countries": "SE - Sweden"
}, {
    "ID": 194,
    "Countries": "SG - Singapore"
}, {
    "ID": 195,
    "Countries": "SH - Saint Helena"
}, {
    "ID": 196,
    "Countries": "SI - Slovenia"
}, {
    "ID": 197,
    "Countries": "SK - Slovakia"
}, {
    "ID": 198,
    "Countries": "SL - Sierra Leone"
}, {
    "ID": 199,
    "Countries": "SM - San Marino"
}, {
    "ID": 200,
    "Countries": "SN - Senegal"
}, {
    "ID": 201,
    "Countries": "SO - Somalia"
}, {
    "ID": 202,
    "Countries": "SR - Suriname"
}, {
    "ID": 203,
    "Countries": "SS - South Sudan"
}, {
    "ID": 204,
    "Countries": "ST - São Tomé and Principe"
}, {
    "ID": 205,
    "Countries": "SV - El Salvador"
}, {
    "ID": 206,
    "Countries": "SX - Sint Maarten"
}, {
    "ID": 207,
    "Countries": "SY - Syria"
}, {
    "ID": 208,
    "Countries": "SZ - Eswatini"
}, {
    "ID": 209,
    "Countries": "TC - Turks and Caicos Islands"
}, {
    "ID": 210,
    "Countries": "TD - Chad"
}, {
    "ID": 211,
    "Countries": "TF - French Southern Territories"
}, {
    "ID": 212,
    "Countries": "TG - Togo"
}, {
    "ID": 213,
    "Countries": "TH - Thailand"
}, {
    "ID": 214,
    "Countries": "TJ - Tajikistan"
}, {
    "ID": 215,
    "Countries": "TK - Tokelau"
}, {
    "ID": 216,
    "Countries": "TL - Timor-Leste"
}, {
    "ID": 217,
    "Countries": "TM - Turkmenistan"
}, {
    "ID": 218,
    "Countries": "TN - Tunisia"
}, {
    "ID": 219,
    "Countries": "TO - Tonga"
}, {
    "ID": 220,
    "Countries": "TR - Turkey"
}, {
    "ID": 221,
    "Countries": "TT - Trinidad and Tobago"
}, {
    "ID": 222,
    "Countries": "TV - Tuvalu"
}, {
    "ID": 223,
    "Countries": "TW - Taiwan"
}, {
    "ID": 224,
    "Countries": "TZ - Tanzania"
}, {
    "ID": 225,
    "Countries": "UA - Ukraine"
}, {
    "ID": 226,
    "Countries": "UG - Uganda"
}, {
    "ID": 227,
    "Countries": "UM - United States Minor Outlying Islands"
}, {
    "ID": 228,
    "Countries": "US - United States"
}, {
    "ID": 229,
    "Countries": "UY - Uruguay"
}, {
    "ID": 230,
    "Countries": "UZ - Uzbekistan"
}, {
    "ID": 231,
    "Countries": "VA - Vatican City"
}, {
    "ID": 232,
    "Countries": "VC - Saint Vincent and the Grenadines"
}, {
    "ID": 233,
    "Countries": "VE - Venezuela"
}, {
    "ID": 234,
    "Countries": "VG - British Virgin Islands"
}, {
    "ID": 235,
    "Countries": "VI - U.S. Virgin Islands"
}, {
    "ID": 236,
    "Countries": "VN - Vietnam"
}, {
    "ID": 237,
    "Countries": "VU - Vanuatu"
}, {
    "ID": 238,
    "Countries": "WF - Wallis and Futuna"
}, {
    "ID": 239,
    "Countries": "WS - Samoa"
}, {
    "ID": 240,
    "Countries": "XK - Kosovo"
}, {
    "ID": 241,
    "Countries": "YE - Yemen"
}, {
    "ID": 242,
    "Countries": "YT - Mayotte"
}, {
    "ID": 243,
    "Countries": "ZA - South Africa"
}, {
    "ID": 244,
    "Countries": "ZM - Zambia"
}, {
    "ID": 245,
    "Countries": "ZW - Zimbabwe"
}, {
    "ID": 246,
    "Countries": "ZZ - Unknown or unassigned country"
}]